napari_zplane_depth_colorizer/__init__.py
napari_zplane_depth_colorizer/_widget copy.py
napari_zplane_depth_colorizer/_widget.py
napari_zplane_depth_colorizer/napari.yaml
napari_zplane_depth_colorizer/_tests/__init__.py
napari_zplane_depth_colorizer/_tests/test_widget.py
napari_zplane_depth_colorizer-0.0.1.dist-info/LICENSE
napari_zplane_depth_colorizer-0.0.1.dist-info/METADATA
napari_zplane_depth_colorizer-0.0.1.dist-info/WHEEL
napari_zplane_depth_colorizer-0.0.1.dist-info/entry_points.txt
napari_zplane_depth_colorizer-0.0.1.dist-info/top_level.txt
napari_zplane_depth_colorizer-0.0.1.dist-info/RECORD
